odoo/addons/stock_vlm_mgmt_modula/README.rst
odoo/addons/stock_vlm_mgmt_modula/__init__.py
odoo/addons/stock_vlm_mgmt_modula/__manifest__.py
odoo/addons/stock_vlm_mgmt_modula/i18n/it.po
odoo/addons/stock_vlm_mgmt_modula/i18n/stock_vlm_mgmt_modula.pot
odoo/addons/stock_vlm_mgmt_modula/models/__init__.py
odoo/addons/stock_vlm_mgmt_modula/models/modula_request.py
odoo/addons/stock_vlm_mgmt_modula/models/stock_location.py
odoo/addons/stock_vlm_mgmt_modula/readme/CONTRIBUTORS.rst
odoo/addons/stock_vlm_mgmt_modula/readme/DESCRIPTION.rst
odoo/addons/stock_vlm_mgmt_modula/readme/ROADMAP.rst
odoo/addons/stock_vlm_mgmt_modula/static/description/icon.png
odoo/addons/stock_vlm_mgmt_modula/static/description/index.html
odoo_addon_stock_vlm_mgmt_modula-16.0.1.0.0.4.dist-info/METADATA
odoo_addon_stock_vlm_mgmt_modula-16.0.1.0.0.4.dist-info/WHEEL
odoo_addon_stock_vlm_mgmt_modula-16.0.1.0.0.4.dist-info/top_level.txt
odoo_addon_stock_vlm_mgmt_modula-16.0.1.0.0.4.dist-info/RECORD
